README.md
setup.cfg
setup.py
nomad_hawk_cli/__init__.py
nomad_hawk_cli/api_client.py
nomad_hawk_cli/append_alibaba_headers.py
nomad_hawk_cli/configuration.py
nomad_hawk_cli/exceptions.py
nomad_hawk_cli/rest.py
nomad_hawk_cli.egg-info/PKG-INFO
nomad_hawk_cli.egg-info/SOURCES.txt
nomad_hawk_cli.egg-info/dependency_links.txt
nomad_hawk_cli.egg-info/requires.txt
nomad_hawk_cli.egg-info/top_level.txt
nomad_hawk_cli/api/__init__.py
nomad_hawk_cli/api/track_api.py
nomad_hawk_cli/models/__init__.py
nomad_hawk_cli/models/api_response.py
nomad_hawk_cli/models/api_response_connector_response.py
nomad_hawk_cli/models/api_response_data.py
nomad_hawk_cli/models/event.py
nomad_hawk_cli/models/event_item.py
test/test_api_response.py
test/test_api_response_connector_response.py
test/test_api_response_data.py
test/test_event.py
test/test_event_item.py
test/test_track_api.py