Metadata-Version: 1.0
Name: nomad-hawk-cli
Version: 1.12.0
Summary: Nomad Hawk
Home-page: UNKNOWN
Author: OpenAPI Generator community
Author-email: paul@samarkand.global
License: UNKNOWN
Keywords: OpenAPI,OpenAPI-Generator,Nomad Hawk
Platform: UNKNOWN
